teacherhelper/__init__.py
teacherhelper/__main__.py
teacherhelper/_data_dir.py
teacherhelper/default_email_template.html
teacherhelper/email_.py
teacherhelper/helper.py
teacherhelper/docx/__init__.py
teacherhelper/docx/_rubric_writer.py
teacherhelper/docx/tests/__init__.py
teacherhelper/docx/tests/test_rubric_writer.py
teacherhelper/docx/tests/assets/sample_rubric.docx
teacherhelper/google/__init__.py
teacherhelper/google/classroom_grader.py
teacherhelper/google/classroom_wrapper.py
teacherhelper/google/client.py
teacherhelper/sis/__init__.py
teacherhelper/sis/_entities.py
teacherhelper/sis/_oncourse_mixin.py
teacherhelper/sis/_sis.py
teacherhelper/sis/tests/__init__.py
teacherhelper/sis/tests/fixtures.py
teacherhelper/sis/tests/random_names.csv
teacherhelper/sis/tests/test_fixtures.py
teacherhelper/sis/tests/test_sis.py
teacherhelper/tests/__init__.py
teacherhelper/tests/test_email.py
teacherhelper/tests/test_helper.py
teacherhelper/tools/__init__.py
teacherhelper/tools/docx_utils.py
teacherhelper-2.0.6.dist-info/LICENSE
teacherhelper-2.0.6.dist-info/METADATA
teacherhelper-2.0.6.dist-info/WHEEL
teacherhelper-2.0.6.dist-info/entry_points.txt
teacherhelper-2.0.6.dist-info/top_level.txt
teacherhelper-2.0.6.dist-info/RECORD
