Metadata-Version: 2.1
Name: teacherhelper
Version: 2.0.6
Summary: Useful abstractions and CLI to make teaching more scriptable.
Home-page: https://github.com/jdevries3133/teacher_helper/
Author: Jack DeVries
Author-email: jdevries3133@gmail.com
Project-URL: Bug Tracker, https://github.com/jdevries3133/teacher_helper/issues/
Project-URL: Documentation, https://teacherhelper.jackdevries.com/
Classifier: Programming Language :: Python :: 3
Classifier: License :: OSI Approved :: MIT License
Classifier: Operating System :: OS Independent
Requires-Python: >=3.8
License-File: LICENSE
Requires-Dist: beautifulsoup4
Requires-Dist: lxml
Requires-Dist: fuzzywuzzy
Requires-Dist: markdown
Requires-Dist: python-docx
Requires-Dist: google-api-python-client
Requires-Dist: google-auth-httplib2
Requires-Dist: google-auth-oauthlib
